coolpackets/__init__.py
coolpackets/exceptions.py
coolpackets/logger.py
coolpackets/packet.py
coolpackets/utils.py
coolpackets-0.0.2.dist-info/LICENSE
coolpackets-0.0.2.dist-info/METADATA
coolpackets-0.0.2.dist-info/WHEEL
coolpackets-0.0.2.dist-info/top_level.txt
coolpackets-0.0.2.dist-info/RECORD
