Metadata-Version: 2.1
Name: coolpackets
Version: 0.0.2
Summary: Packet system for python TCP sockets.
Home-page: https://github.com/timwoocker/coolpackets
Author: Tim Woocker
Author-email: tim.woocker@googlemail.com
License: UNKNOWN
Platform: UNKNOWN
Classifier: Programming Language :: Python :: 3
Classifier: License :: OSI Approved :: MIT License
Classifier: Operating System :: OS Independent
